{
    "bean": {
        "_v": 0,
        "addr": "93.115.240.88",
        "brutal_speed": 0,
        "c_cfg": "",
        "c_out": "",
        "enable_brutal": false,
        "flow": "",
        "mux": 0,
        "name": "🇦🇲 AM | 🔓 VLESS | @server444 [3]",
        "pass": "490edb5c-d884-4b77-be02-19ebad7891dd",
        "port": 20000,
        "stream": {
            "alpn": "",
            "cert": "",
            "ed_len": 0,
            "ed_name": "",
            "h_type": "",
            "headers": "",
            "host": "",
            "insecure": false,
            "method": "",
            "net": "ws",
            "pac_enc": "xudp",
            "path": "",
            "pbk": "",
            "sec": "",
            "sid": "",
            "sni": "",
            "tls_frag": false,
            "tls_frag_fall_delay": "",
            "tls_record_frag": false,
            "utls": ""
        }
    },
    "dl": "",
    "gid": 1,
    "id": 196,
    "report": "",
    "traffic": {
        "dl": 0,
        "ul": 0
    },
    "type": "vless",
    "ul": "",
    "yc": -1
}
