{
    "bean": {
        "_v": 0,
        "addr": "34.203.13.163",
        "brutal_speed": 0,
        "c_cfg": "",
        "c_out": "",
        "enable_brutal": false,
        "method": "aes-256-cfb",
        "mux": 0,
        "name": "tg频道:@ripaojiedian",
        "pass": "amazonskr05",
        "plugin": "",
        "port": 443,
        "stream": {
            "alpn": "",
            "cert": "",
            "ed_len": 0,
            "ed_name": "",
            "h_type": "",
            "headers": "",
            "host": "",
            "insecure": false,
            "method": "",
            "net": "tcp",
            "pac_enc": "",
            "path": "",
            "pbk": "",
            "sec": "",
            "sid": "",
            "sni": "",
            "utls": ""
        },
        "uot": 0
    },
    "dl": "",
    "gid": 2,
    "id": 4323,
    "report": "",
    "traffic": {
        "dl": 0,
        "ul": 0
    },
    "type": "shadowsocks",
    "ul": "",
    "yc": -1
}
